{
 "badge": "http://software-carpentry.org/badges/class/instructor.json", 
 "image": "http://software-carpentry.org/img/badges/instructor.png", 
 "issuedOn": "2014-12-08", 
 "recipient": {
  "hashed": true, 
  "identity": "sha256$0518e8879270888ba450bcf87737b5ea05e77e3e66442cef8af0771e3b6174bf", 
  "salt": "software-carpentry", 
  "type": "email"
 }, 
 "uid": "sha256$0518e8879270888ba450bcf87737b5ea05e77e3e66442cef8af0771e3b6174bf", 
 "verify": {
  "type": "hosted", 
  "url": "http://software-carpentry.org/badges/instructor/gates.chris.json"
 }
}