{
  "recipient" : "sha256$a198eef32544943238963b0f05cbac0d8cb2c458e5b187a589bd03306d944931",
  "salt": "software-carpentry",
  "issued_on" : "2013-03-16",
  "badge" : {
    "version" : "0.5.0",
    "name" : "Organizer",
    "image" : "/img/badges/organizer.png",
    "description" : "Organizing workshops and learning groups",
    "criteria" : "/badges/organizer.html",
    "issuer" : {
      "origin" : "http://software-carpentry.org",
      "name" : "Software Carpentry",
      "contact" : "admin@software-carpentry.org"
    }
  }
}